{
    "Description": {
        "Id": "lancedef_mech_d2_dynamic_solo_1_EA_Elite",
        "Name": "Dynamic Dif 2 Solo Elite 1",
        "Details": "",
        "Icon": "",
        "Cost": 0,
        "Rarity": 0,
        "Purchasable": false
    },
    "Difficulty": 2,
    "LanceTags": {
        "items": [
            "lance_type_dynamic",
            "lance_type_solo",
            "lance_type_mech",
            "elite_arsenal"
        ],
        "tagSetSourceFile": "Tags/LanceTags"
    },
    "LanceUnits": [
        {
            "unitType": "Mech",
            "unitId": "Tagged",
            "pilotId": "Tagged",
            "unitTagSet": {
                "items": [
                    "unit_mech",
                    "unit_medium",
                    "elite_arsenal"
                ],
                "tagSetSourceFile": "Tags/UnitTags"
            },
            "excludedUnitTagSet": {
                "items": [
                    "unit_urbie"
                ],
                "tagSetSourceFile": "Tags/UnitTags"
            },
            "pilotTagSet": {
                "items": [
                    "pilot_npc_d6_elite_arsenal"
                ],
                "tagSetSourceFile": "Tags/PilotTags"
            },
            "excludedPilotTagSet": {
                "items": null,
                "tagSetSourceFile": "Tags/PilotTags"
            }
        },
        {
            "unitType": "Mech",
            "unitId": "Tagged",
            "pilotId": "Tagged",
            "unitTagSet": {
                "items": [
                    "unit_light",
                    "unit_mech",
                    "elite_arsenal"
                ],
                "tagSetSourceFile": "Tags/UnitTags"
            },
            "excludedUnitTagSet": {
                "items": [
                    "unit_urbie"
                ],
                "tagSetSourceFile": "Tags/UnitTags"
            },
            "pilotTagSet": {
                "items": [
                    "pilot_npc_d2_elite_arsenal"
                ],
                "tagSetSourceFile": "Tags/PilotTags"
            },
            "excludedPilotTagSet": {
                "items": null,
                "tagSetSourceFile": "Tags/PilotTags"
            }
        }
    ]
}

